[
  {
    "name": "create_file",
    "description": "Create a new file with specified content",
    "type": "function",
    "parameters": {"filePath": "string", "content": "string"},
    "code": "def execute(params):\n    \"\"\"Create a new file with specified content.\"\"\"\n    import os\n\n    file_path = params.get('filePath')\n    if not file_path:\n        return {'success': False, 'error': 'filePath parameter is required'}\n\n    content = params.get('content', '')\n    dir_path = os.path.dirname(file_path)\n    if dir_path:\n        os.makedirs(dir_path, exist_ok=True)\n\n    with open(file_path, 'w') as f:\n        f.write(content)\n\n    return {\n        'success': True,\n        'message': f'File created: {file_path}',\n        'filePath': file_path,\n        'size': len(content)\n    }",
    "enabled": true
  },
  {
    "name": "read_file",
    "description": "Read contents of a file",
    "type": "function",
    "parameters": {"filePath": "string"},
    "code": "def execute(params):\n    \"\"\"Read contents of a file.\"\"\"\n    file_path = params.get('filePath')\n    if not file_path:\n        return {'success': False, 'error': 'filePath parameter is required'}\n\n    try:\n        with open(file_path, 'r') as f:\n            content = f.read()\n        return {\n            'success': True,\n            'content': content,\n            'filePath': file_path,\n            'size': len(content)\n        }\n    except FileNotFoundError:\n        return {'success': False, 'error': f'File not found: {file_path}'}\n    except Exception as e:\n        return {'success': False, 'error': str(e)}",
    "enabled": true
  },
  {
    "name": "update_file",
    "description": "Update an existing file with new content",
    "type": "function",
    "parameters": {"filePath": "string", "content": "string"},
    "code": "def execute(params):\n    \"\"\"Update an existing file with new content.\"\"\"\n    file_path = params.get('filePath')\n    if not file_path:\n        return {'success': False, 'error': 'filePath parameter is required'}\n\n    content = params.get('content', '')\n\n    with open(file_path, 'w') as f:\n        f.write(content)\n\n    return {\n        'success': True,\n        'message': f'File updated: {file_path}',\n        'filePath': file_path,\n        'size': len(content)\n    }",
    "enabled": true
  },
  {
    "name": "delete_file",
    "description": "Delete a file from the filesystem",
    "type": "function",
    "parameters": {"filePath": "string"},
    "code": "def execute(params):\n    \"\"\"Delete a file from the filesystem.\"\"\"\n    import os\n\n    file_path = params.get('filePath')\n    if not file_path:\n        return {'success': False, 'error': 'filePath parameter is required'}\n\n    try:\n        os.remove(file_path)\n        return {\n            'success': True,\n            'message': f'File deleted: {file_path}'\n        }\n    except FileNotFoundError:\n        return {'success': False, 'error': f'File not found: {file_path}'}\n    except Exception as e:\n        return {'success': False, 'error': str(e)}",
    "enabled": true
  },
  {
    "name": "delete_directory",
    "description": "Delete a directory and all its contents recursively",
    "type": "function",
    "parameters": {"dirPath": "string"},
    "code": "def execute(params):\n    \"\"\"Delete a directory and all its contents recursively.\"\"\"\n    import shutil\n    import os\n\n    dir_path = params.get('dirPath')\n    if not dir_path:\n        return {'success': False, 'error': 'dirPath parameter is required'}\n\n    try:\n        if os.path.isfile(dir_path):\n            return {'success': False, 'error': f'Path is a file, not a directory. Use delete_file instead: {dir_path}'}\n        \n        if not os.path.exists(dir_path):\n            return {'success': False, 'error': f'Directory not found: {dir_path}'}\n        \n        shutil.rmtree(dir_path)\n        return {\n            'success': True,\n            'message': f'Directory deleted: {dir_path}'\n        }\n    except Exception as e:\n        return {'success': False, 'error': str(e)}",
    "enabled": true
  },
  {
    "name": "list_directory",
    "description": "List all files and directories in a path",
    "type": "function",
    "parameters": {"dirPath": "string", "recursive": "boolean"},
    "code": "def execute(params):\n    \"\"\"List all files and directories in a path.\"\"\"\n    import os\n\n    dir_path = params.get('dirPath')\n    if not dir_path:\n        return {'success': False, 'error': 'dirPath parameter is required'}\n\n    recursive = params.get('recursive', False)\n\n    try:\n        if recursive:\n            files = []\n            for root, dirs, filenames in os.walk(dir_path):\n                for filename in filenames:\n                    files.append(os.path.join(root, filename))\n        else:\n            files = os.listdir(dir_path)\n\n        return {\n            'success': True,\n            'files': files,\n            'count': len(files)\n        }\n    except Exception as e:\n        return {'success': False, 'error': str(e)}",
    "enabled": true
  },
  {
    "name": "move_file",
    "description": "Move or rename a file",
    "type": "function",
    "parameters": {"sourcePath": "string", "destPath": "string"},
    "code": "def execute(params):\n    \"\"\"Move or rename a file.\"\"\"\n    import shutil\n\n    source_path = params.get('sourcePath')\n    dest_path = params.get('destPath')\n\n    if not source_path or not dest_path:\n        return {'success': False, 'error': 'sourcePath and destPath parameters are required'}\n\n    try:\n        shutil.move(source_path, dest_path)\n        return {\n            'success': True,\n            'message': f'File moved: {source_path} -> {dest_path}'\n        }\n    except Exception as e:\n        return {'success': False, 'error': str(e)}",
    "enabled": true
  },
  {
    "name": "copy_file",
    "description": "Copy a file to a new location",
    "type": "function",
    "parameters": {"sourcePath": "string", "destPath": "string"},
    "code": "def execute(params):\n    \"\"\"Copy a file to a new location.\"\"\"\n    import shutil\n\n    source_path = params.get('sourcePath')\n    dest_path = params.get('destPath')\n\n    if not source_path or not dest_path:\n        return {'success': False, 'error': 'sourcePath and destPath parameters are required'}\n\n    try:\n        shutil.copy2(source_path, dest_path)\n        return {\n            'success': True,\n            'message': f'File copied: {source_path} -> {dest_path}'\n        }\n    except Exception as e:\n        return {'success': False, 'error': str(e)}",
    "enabled": true
  },
  {
    "name": "fetch_url",
    "description": "Fetch content from a URL",
    "type": "tool",
    "parameters": {"url": "string", "method": "string", "headers": "object", "timeout": "number"},
    "code": "def execute(params):\n    \"\"\"Fetch content from a URL.\"\"\"\n    import urllib.request\n    import urllib.error\n    import json\n\n    url = params.get('url')\n    if not url:\n        return {'success': False, 'error': 'url parameter is required'}\n\n    method = params.get('method', 'GET').upper()\n    headers = params.get('headers', {})\n    timeout = params.get('timeout', 30)\n\n    try:\n        req = urllib.request.Request(url, method=method)\n        for key, value in headers.items():\n            req.add_header(key, value)\n\n        with urllib.request.urlopen(req, timeout=timeout) as response:\n            content = response.read().decode('utf-8')\n            return {\n                'success': True,\n                'status': response.status,\n                'headers': dict(response.headers),\n                'content': content,\n                'url': url\n            }\n    except urllib.error.HTTPError as e:\n        return {\n            'success': False,\n            'error': f'HTTP {e.code}: {e.reason}',\n            'status': e.code\n        }\n    except Exception as e:\n        return {'success': False, 'error': str(e)}",
    "enabled": true
  },
  {
    "name": "dns_lookup",
    "description": "Perform DNS lookup for a domain",
    "type": "tool",
    "parameters": {"domain": "string"},
    "code": "def execute(params):\n    \"\"\"Perform DNS lookup for a domain.\"\"\"\n    import socket\n\n    domain = params.get('domain')\n    if not domain:\n        return {'success': False, 'error': 'domain parameter is required'}\n\n    try:\n        ipv4 = socket.gethostbyname(domain)\n        return {\n            'success': True,\n            'domain': domain,\n            'ipv4': ipv4\n        }\n    except socket.gaierror as e:\n        return {'success': False, 'error': f'DNS lookup failed: {str(e)}'}",
    "enabled": true
  },
  {
    "name": "check_port",
    "description": "Check if a port is open on a host",
    "type": "tool",
    "parameters": {"host": "string", "port": "number", "timeout": "number"},
    "code": "def execute(params):\n    \"\"\"Check if a port is open on a host.\"\"\"\n    import socket\n\n    host = params.get('host')\n    port = params.get('port')\n\n    if not host or not port:\n        return {'success': False, 'error': 'host and port parameters are required'}\n\n    timeout = params.get('timeout', 5)\n\n    try:\n        sock = socket.socket(socket.AF_INET, socket.SOCK_STREAM)\n        sock.settimeout(timeout)\n        result = sock.connect_ex((host, int(port)))\n        sock.close()\n\n        return {\n            'success': True,\n            'host': host,\n            'port': port,\n            'open': result == 0\n        }\n    except Exception as e:\n        return {'success': False, 'error': str(e)}",
    "enabled": true
  },
  {
    "name": "ping_host",
    "description": "Ping a host to check connectivity",
    "type": "tool",
    "parameters": {"host": "string", "count": "number"},
    "code": "def execute(params):\n    \"\"\"Ping a host to check connectivity.\"\"\"\n    import subprocess\n    import platform\n\n    host = params.get('host')\n    if not host:\n        return {'success': False, 'error': 'host parameter is required'}\n\n    count = params.get('count', 4)\n    system = platform.system().lower()\n\n    try:\n        if system == 'windows':\n            cmd = ['ping', '-n', str(count), host]\n        else:\n            cmd = ['ping', '-c', str(count), host]\n\n        result = subprocess.run(cmd, capture_output=True, text=True, timeout=30)\n\n        return {\n            'success': True,\n            'host': host,\n            'count': count,\n            'output': result.stdout,\n            'reachable': result.returncode == 0\n        }\n    except Exception as e:\n        return {'success': False, 'error': str(e)}",
    "enabled": true
  },
  {
    "name": "http_request",
    "description": "Make custom HTTP requests (GET, POST, PUT, DELETE)",
    "type": "tool",
    "parameters": {"url": "string", "method": "string", "headers": "object", "body": "string"},
    "code": "def execute(params):\n    \"\"\"Make custom HTTP requests.\"\"\"\n    import urllib.request\n    import urllib.error\n    import json\n\n    url = params.get('url')\n    if not url:\n        return {'success': False, 'error': 'url parameter is required'}\n\n    method = params.get('method', 'GET').upper()\n    headers = params.get('headers', {})\n    body = params.get('body')\n\n    try:\n        data = body.encode('utf-8') if body else None\n        req = urllib.request.Request(url, data=data, method=method)\n\n        for key, value in headers.items():\n            req.add_header(key, value)\n\n        with urllib.request.urlopen(req, timeout=30) as response:\n            content = response.read().decode('utf-8')\n            return {\n                'success': True,\n                'status': response.status,\n                'headers': dict(response.headers),\n                'data': content\n            }\n    except urllib.error.HTTPError as e:\n        return {\n            'success': False,\n            'error': f'HTTP {e.code}: {e.reason}',\n            'status': e.code\n        }\n    except Exception as e:\n        return {'success': False, 'error': str(e)}",
    "enabled": true
  },
  {
    "name": "run_bash",
    "description": "Execute bash commands on Linux/macOS",
    "type": "command",
    "parameters": {"command": "string", "timeout": "number"},
    "code": "def execute(params):\n    \"\"\"Execute bash commands.\"\"\"\n    import subprocess\n\n    command = params.get('command')\n    if not command:\n        return {'success': False, 'error': 'command parameter is required'}\n\n    timeout = params.get('timeout', 30)\n\n    try:\n        result = subprocess.run(\n            command,\n            shell=True,\n            capture_output=True,\n            text=True,\n            timeout=timeout,\n            executable='/bin/bash'\n        )\n\n        return {\n            'success': True,\n            'stdout': result.stdout,\n            'stderr': result.stderr,\n            'returncode': result.returncode\n        }\n    except subprocess.TimeoutExpired:\n        return {'success': False, 'error': f'Command timed out after {timeout} seconds'}\n    except Exception as e:\n        return {'success': False, 'error': str(e)}",
    "enabled": false
  },
  {
    "name": "run_python",
    "description": "Execute Python code",
    "type": "command",
    "parameters": {"code": "string", "timeout": "number"},
    "code": "def execute(params):\n    \"\"\"Execute Python code.\"\"\"\n    import subprocess\n    import tempfile\n    import os\n\n    code = params.get('code')\n    if not code:\n        return {'success': False, 'error': 'code parameter is required'}\n\n    timeout = params.get('timeout', 30)\n\n    try:\n        with tempfile.NamedTemporaryFile(mode='w', suffix='.py', delete=False) as f:\n            f.write(code)\n            temp_file = f.name\n\n        result = subprocess.run(\n            ['python3', temp_file],\n            capture_output=True,\n            text=True,\n            timeout=timeout\n        )\n\n        os.remove(temp_file)\n\n        return {\n            'success': True,\n            'stdout': result.stdout,\n            'stderr': result.stderr,\n            'returncode': result.returncode\n        }\n    except subprocess.TimeoutExpired:\n        os.remove(temp_file) if 'temp_file' in locals() else None\n        return {'success': False, 'error': f'Code execution timed out after {timeout} seconds'}\n    except Exception as e:\n        os.remove(temp_file) if 'temp_file' in locals() else None\n        return {'success': False, 'error': str(e)}",
    "enabled": false
  },
  {
    "name": "system_info",
    "description": "Get system information (CPU, memory, disk)",
    "type": "command",
    "parameters": {},
    "code": "def execute(params):\n    \"\"\"Get system information.\"\"\"\n    import platform\n    import psutil\n\n    try:\n        cpu_percent = psutil.cpu_percent(interval=1)\n        memory = psutil.virtual_memory()\n        disk = psutil.disk_usage('/')\n\n        return {\n            'success': True,\n            'platform': platform.system(),\n            'platform_release': platform.release(),\n            'architecture': platform.machine(),\n            'hostname': platform.node(),\n            'processor': platform.processor(),\n            'cpu': {\n                'cores': psutil.cpu_count(logical=False),\n                'threads': psutil.cpu_count(logical=True),\n                'percent': cpu_percent\n            },\n            'memory': {\n                'total': memory.total,\n                'available': memory.available,\n                'percent': memory.percent\n            },\n            'disk': {\n                'total': disk.total,\n                'used': disk.used,\n                'free': disk.free,\n                'percent': disk.percent\n            }\n        }\n    except ImportError:\n        return {'success': False, 'error': 'psutil module not installed. Install with: pip install psutil'}\n    except Exception as e:\n        return {'success': False, 'error': str(e)}",
    "enabled": true
  },
  {
    "name": "parse_json",
    "description": "Parse and validate JSON data",
    "type": "function",
    "parameters": {"jsonString": "string"},
    "code": "def execute(params):\n    \"\"\"Parse and validate JSON data.\"\"\"\n    import json\n\n    json_string = params.get('jsonString')\n    if not json_string:\n        return {'success': False, 'error': 'jsonString parameter is required'}\n\n    try:\n        data = json.loads(json_string)\n        return {\n            'success': True,\n            'data': data,\n            'type': type(data).__name__\n        }\n    except json.JSONDecodeError as e:\n        return {\n            'success': False,\n            'error': f'Invalid JSON: {str(e)}'\n        }",
    "enabled": true
  },
  {
    "name": "parse_csv",
    "description": "Parse CSV data into structured format",
    "type": "function",
    "parameters": {"csvString": "string", "delimiter": "string"},
    "code": "def execute(params):\n    \"\"\"Parse CSV data into structured format.\"\"\"\n    import csv\n    import io\n\n    csv_string = params.get('csvString')\n    if not csv_string:\n        return {'success': False, 'error': 'csvString parameter is required'}\n\n    delimiter = params.get('delimiter', ',')\n\n    try:\n        reader = csv.DictReader(io.StringIO(csv_string), delimiter=delimiter)\n        data = list(reader)\n\n        return {\n            'success': True,\n            'data': data,\n            'rows': len(data),\n            'columns': list(data[0].keys()) if data else []\n        }\n    except Exception as e:\n        return {'success': False, 'error': str(e)}",
    "enabled": true
  },
  {
    "name": "base64_encode",
    "description": "Encode data to Base64",
    "type": "function",
    "parameters": {"data": "string"},
    "code": "def execute(params):\n    \"\"\"Encode data to Base64.\"\"\"\n    import base64\n\n    data = params.get('data')\n    if not data:\n        return {'success': False, 'error': 'data parameter is required'}\n\n    try:\n        encoded = base64.b64encode(data.encode('utf-8')).decode('utf-8')\n        return {\n            'success': True,\n            'encoded': encoded\n        }\n    except Exception as e:\n        return {'success': False, 'error': str(e)}",
    "enabled": true
  },
  {
    "name": "base64_decode",
    "description": "Decode Base64 data",
    "type": "function",
    "parameters": {"encodedData": "string"},
    "code": "def execute(params):\n    \"\"\"Decode Base64 data.\"\"\"\n    import base64\n\n    encoded_data = params.get('encodedData')\n    if not encoded_data:\n        return {'success': False, 'error': 'encodedData parameter is required'}\n\n    try:\n        decoded = base64.b64decode(encoded_data).decode('utf-8')\n        return {\n            'success': True,\n            'decoded': decoded\n        }\n    except Exception as e:\n        return {'success': False, 'error': f'Invalid base64 data: {str(e)}'}",
    "enabled": true
  },
  {
    "name": "hash_data",
    "description": "Generate hash (MD5, SHA1, SHA256) of data",
    "type": "function",
    "parameters": {"data": "string", "algorithm": "string"},
    "code": "def execute(params):\n    \"\"\"Generate hash of data.\"\"\"\n    import hashlib\n\n    data = params.get('data')\n    if not data:\n        return {'success': False, 'error': 'data parameter is required'}\n\n    algorithm = params.get('algorithm', 'sha256').lower()\n\n    try:\n        if algorithm == 'md5':\n            h = hashlib.md5()\n        elif algorithm == 'sha1':\n            h = hashlib.sha1()\n        elif algorithm == 'sha256':\n            h = hashlib.sha256()\n        elif algorithm == 'sha512':\n            h = hashlib.sha512()\n        else:\n            return {'success': False, 'error': f'Unsupported algorithm: {algorithm}'}\n\n        h.update(data.encode('utf-8'))\n\n        return {\n            'success': True,\n            'hash': h.hexdigest(),\n            'algorithm': algorithm\n        }\n    except Exception as e:\n        return {'success': False, 'error': str(e)}",
    "enabled": true
  },
  {
    "name": "generate_uuid",
    "description": "Generate a UUID (v4)",
    "type": "function",
    "parameters": {},
    "code": "def execute(params):\n    \"\"\"Generate a UUID.\"\"\"\n    import uuid\n\n    return {\n        'success': True,\n        'uuid': str(uuid.uuid4())\n    }",
    "enabled": true
  },
  {
    "name": "get_timestamp",
    "description": "Get current timestamp in various formats",
    "type": "function",
    "parameters": {"format": "string"},
    "code": "def execute(params):\n    \"\"\"Get current timestamp.\"\"\"\n    import datetime\n    import time\n\n    fmt = params.get('format', 'iso')\n    now = datetime.datetime.now()\n\n    formats = {\n        'iso': now.isoformat(),\n        'unix': int(time.time()),\n        'date': now.strftime('%Y-%m-%d'),\n        'time': now.strftime('%H:%M:%S'),\n        'datetime': now.strftime('%Y-%m-%d %H:%M:%S')\n    }\n\n    if fmt in formats:\n        return {\n            'success': True,\n            'timestamp': formats[fmt],\n            'format': fmt\n        }\n    else:\n        return {\n            'success': True,\n            'timestamp': now.strftime(fmt),\n            'format': 'custom'\n        }",
    "enabled": true
  },
  {
    "name": "find_patterns",
    "description": "Search for regex patterns in text",
    "type": "tool",
    "parameters": {"text": "string", "pattern": "string", "flags": "string"},
    "code": "def execute(params):\n    \"\"\"Search for regex patterns in text.\"\"\"\n    import re\n\n    text = params.get('text')\n    pattern = params.get('pattern')\n\n    if not text or not pattern:\n        return {'success': False, 'error': 'text and pattern parameters are required'}\n\n    flags_str = params.get('flags', '')\n    flags = 0\n    if 'i' in flags_str:\n        flags |= re.IGNORECASE\n    if 'm' in flags_str:\n        flags |= re.MULTILINE\n    if 's' in flags_str:\n        flags |= re.DOTALL\n\n    try:\n        matches = re.finditer(pattern, text, flags)\n        results = []\n        for match in matches:\n            results.append({\n                'match': match.group(),\n                'start': match.start(),\n                'end': match.end(),\n                'groups': match.groups()\n            })\n\n        return {\n            'success': True,\n            'count': len(results),\n            'matches': results\n        }\n    except re.error as e:\n        return {'success': False, 'error': f'Invalid regex pattern: {str(e)}'}",
    "enabled": true
  },
  {
    "name": "analyze_code",
    "description": "Analyze code for basic metrics",
    "type": "tool",
    "parameters": {"code": "string", "language": "string"},
    "code": "def execute(params):\n    \"\"\"Analyze code for basic metrics.\"\"\"\n    code = params.get('code')\n    if not code:\n        return {'success': False, 'error': 'code parameter is required'}\n\n    language = params.get('language', 'unknown')\n    lines = code.split('\\n')\n    non_empty_lines = [l for l in lines if l.strip()]\n\n    # Detect comment patterns based on language\n    comment_patterns = ['#', '//', '/*', '*', '<!--']\n    comment_lines = [l for l in lines if any(l.strip().startswith(p) for p in comment_patterns)]\n\n    return {\n        'success': True,\n        'language': language,\n        'total_lines': len(lines),\n        'code_lines': len(non_empty_lines),\n        'comment_lines': len(comment_lines),\n        'blank_lines': len(lines) - len(non_empty_lines),\n        'avg_line_length': sum(len(l) for l in lines) / len(lines) if lines else 0\n    }",
    "enabled": true
  },
  {
    "name": "count_words",
    "description": "Count words in text",
    "type": "function",
    "parameters": {"text": "string"},
    "code": "def execute(params):\n    \"\"\"Count words in text.\"\"\"\n    text = params.get('text')\n    if not text:\n        return {'success': False, 'error': 'text parameter is required'}\n\n    words = text.split()\n    unique_words = set(words)\n\n    return {\n        'success': True,\n        'total_words': len(words),\n        'unique_words': len(unique_words),\n        'characters': len(text),\n        'lines': len(text.split('\\n'))\n    }",
    "enabled": true
  },
  {
    "name": "compress_data",
    "description": "Compress data using gzip",
    "type": "function",
    "parameters": {"data": "string"},
    "code": "def execute(params):\n    \"\"\"Compress data using gzip.\"\"\"\n    import gzip\n    import base64\n\n    data = params.get('data')\n    if not data:\n        return {'success': False, 'error': 'data parameter is required'}\n\n    try:\n        compressed = gzip.compress(data.encode('utf-8'))\n        encoded = base64.b64encode(compressed).decode('utf-8')\n\n        return {\n            'success': True,\n            'compressed': encoded,\n            'original_size': len(data),\n            'compressed_size': len(compressed),\n            'ratio': f'{len(compressed) / len(data) * 100:.2f}%'\n        }\n    except Exception as e:\n        return {'success': False, 'error': str(e)}",
    "enabled": true
  },
  {
    "name": "decompress_data",
    "description": "Decompress gzip data",
    "type": "function",
    "parameters": {"compressedData": "string"},
    "code": "def execute(params):\n    \"\"\"Decompress gzip data.\"\"\"\n    import gzip\n    import base64\n\n    compressed_data = params.get('compressedData')\n    if not compressed_data:\n        return {'success': False, 'error': 'compressedData parameter is required'}\n\n    try:\n        decoded = base64.b64decode(compressed_data)\n        decompressed = gzip.decompress(decoded).decode('utf-8')\n\n        return {\n            'success': True,\n            'decompressed': decompressed,\n            'size': len(decompressed)\n        }\n    except Exception as e:\n        return {'success': False, 'error': str(e)}",
    "enabled": true
  },
  {
    "name": "run_powershell",
    "description": "Execute PowerShell commands on Windows",
    "type": "command",
    "parameters": {"command": "string", "timeout": "number"},
    "code": "def execute(params):\n    \"\"\"Execute PowerShell commands.\"\"\"\n    import subprocess\n    import platform\n\n    if platform.system() != 'Windows':\n        return {'success': False, 'error': 'PowerShell is only available on Windows'}\n\n    command = params.get('command')\n    if not command:\n        return {'success': False, 'error': 'command parameter is required'}\n\n    timeout = params.get('timeout', 30)\n\n    try:\n        result = subprocess.run(\n            ['powershell', '-Command', command],\n            capture_output=True,\n            text=True,\n            timeout=timeout\n        )\n\n        return {\n            'success': True,\n            'stdout': result.stdout,\n            'stderr': result.stderr,\n            'returncode': result.returncode\n        }\n    except subprocess.TimeoutExpired:\n        return {'success': False, 'error': f'Command timed out after {timeout} seconds'}\n    except Exception as e:\n        return {'success': False, 'error': str(e)}",
    "enabled": false
  },
  {
    "name": "run_cmd",
    "description": "Execute cmd.exe commands on Windows",
    "type": "command",
    "parameters": {"command": "string", "timeout": "number"},
    "code": "def execute(params):\n    \"\"\"Execute cmd.exe commands.\"\"\"\n    import subprocess\n    import platform\n\n    if platform.system() != 'Windows':\n        return {'success': False, 'error': 'cmd.exe is only available on Windows'}\n\n    command = params.get('command')\n    if not command:\n        return {'success': False, 'error': 'command parameter is required'}\n\n    timeout = params.get('timeout', 30)\n\n    try:\n        result = subprocess.run(\n            ['cmd', '/c', command],\n            capture_output=True,\n            text=True,\n            timeout=timeout\n        )\n\n        return {\n            'success': True,\n            'stdout': result.stdout,\n            'stderr': result.stderr,\n            'returncode': result.returncode\n        }\n    except subprocess.TimeoutExpired:\n        return {'success': False, 'error': f'Command timed out after {timeout} seconds'}\n    except Exception as e:\n        return {'success': False, 'error': str(e)}",
    "enabled": false
  },
  {
    "name": "get_windows_services",
    "description": "List Windows services and their status",
    "type": "command",
    "parameters": {"serviceName": "string"},
    "code": "def execute(params):\n    \"\"\"List Windows services.\"\"\"\n    import subprocess\n    import platform\n\n    if platform.system() != 'Windows':\n        return {'success': False, 'error': 'Windows services are only available on Windows'}\n\n    service_name = params.get('serviceName')\n\n    try:\n        if service_name:\n            cmd = ['sc', 'query', service_name]\n        else:\n            cmd = ['sc', 'query']\n\n        result = subprocess.run(cmd, capture_output=True, text=True, timeout=30)\n\n        return {\n            'success': True,\n            'output': result.stdout,\n            'returncode': result.returncode\n        }\n    except Exception as e:\n        return {'success': False, 'error': str(e)}",
    "enabled": false
  },
  {
    "name": "get_registry_value",
    "description": "Read Windows registry value",
    "type": "command",
    "parameters": {"key": "string", "valueName": "string"},
    "code": "def execute(params):\n    \"\"\"Read Windows registry value.\"\"\"\n    import subprocess\n    import platform\n\n    if platform.system() != 'Windows':\n        return {'success': False, 'error': 'Windows registry is only available on Windows'}\n\n    key = params.get('key')\n    value_name = params.get('valueName')\n\n    if not key or not value_name:\n        return {'success': False, 'error': 'key and valueName parameters are required'}\n\n    try:\n        cmd = ['reg', 'query', key, '/v', value_name]\n        result = subprocess.run(cmd, capture_output=True, text=True, timeout=30)\n\n        return {\n            'success': result.returncode == 0,\n            'output': result.stdout,\n            'stderr': result.stderr,\n            'returncode': result.returncode\n        }\n    except Exception as e:\n        return {'success': False, 'error': str(e)}",
    "enabled": false
  },
  {
    "name": "set_registry_value",
    "description": "Write Windows registry value (requires admin)",
    "type": "command",
    "parameters": {"key": "string", "valueName": "string", "valueType": "string", "data": "string"},
    "code": "def execute(params):\n    \"\"\"Write Windows registry value.\"\"\"\n    import subprocess\n    import platform\n\n    if platform.system() != 'Windows':\n        return {'success': False, 'error': 'Windows registry is only available on Windows'}\n\n    key = params.get('key')\n    value_name = params.get('valueName')\n    value_type = params.get('valueType', 'REG_SZ')\n    data = params.get('data')\n\n    if not key or not value_name or not data:\n        return {'success': False, 'error': 'key, valueName, and data parameters are required'}\n\n    try:\n        cmd = ['reg', 'add', key, '/v', value_name, '/t', value_type, '/d', data, '/f']\n        result = subprocess.run(cmd, capture_output=True, text=True, timeout=30)\n\n        return {\n            'success': result.returncode == 0,\n            'output': result.stdout,\n            'stderr': result.stderr,\n            'returncode': result.returncode\n        }\n    except Exception as e:\n        return {'success': False, 'error': str(e)}",
    "enabled": false
  },
  {
    "name": "ocr_image",
    "description": "Extract text from an image using OCR (requires pytesseract)",
    "type": "tool",
    "parameters": {"imagePath": "string", "language": "string"},
    "code": "def execute(params):\n    \"\"\"Extract text from an image using OCR.\"\"\"\n    image_path = params.get('imagePath')\n    if not image_path:\n        return {'success': False, 'error': 'imagePath parameter is required'}\n\n    language = params.get('language', 'eng')\n\n    try:\n        import pytesseract\n        from PIL import Image\n\n        img = Image.open(image_path)\n        text = pytesseract.image_to_string(img, lang=language)\n\n        return {\n            'success': True,\n            'text': text,\n            'language': language,\n            'imagePath': image_path\n        }\n    except ImportError:\n        return {'success': False, 'error': 'pytesseract and/or PIL not installed. Install with: pip install pytesseract pillow'}\n    except Exception as e:\n        return {'success': False, 'error': str(e)}",
    "enabled": true
  },
  {
    "name": "unzip_file",
    "description": "Extract a ZIP archive to a directory",
    "type": "function",
    "parameters": {"zipPath": "string", "extractPath": "string"},
    "code": "def execute(params):\n    \"\"\"Extract a ZIP archive.\"\"\"\n    import zipfile\n    import os\n\n    zip_path = params.get('zipPath')\n    extract_path = params.get('extractPath')\n\n    if not zip_path:\n        return {'success': False, 'error': 'zipPath parameter is required'}\n\n    if not extract_path:\n        extract_path = os.path.dirname(zip_path)\n\n    try:\n        with zipfile.ZipFile(zip_path, 'r') as zip_ref:\n            zip_ref.extractall(extract_path)\n            file_list = zip_ref.namelist()\n\n        return {\n            'success': True,\n            'message': f'Extracted {len(file_list)} files',\n            'files': file_list,\n            'extractPath': extract_path\n        }\n    except zipfile.BadZipFile:\n        return {'success': False, 'error': 'Invalid or corrupted ZIP file'}\n    except Exception as e:\n        return {'success': False, 'error': str(e)}",
    "enabled": true
  },
  {
    "name": "zip_files",
    "description": "Create a ZIP archive from files/directories",
    "type": "function",
    "parameters": {"zipPath": "string", "sourcePaths": "array"},
    "code": "def execute(params):\n    \"\"\"Create a ZIP archive.\"\"\"\n    import zipfile\n    import os\n\n    zip_path = params.get('zipPath')\n    source_paths = params.get('sourcePaths', [])\n\n    if not zip_path:\n        return {'success': False, 'error': 'zipPath parameter is required'}\n\n    if not source_paths:\n        return {'success': False, 'error': 'sourcePaths parameter is required'}\n\n    try:\n        with zipfile.ZipFile(zip_path, 'w', zipfile.ZIP_DEFLATED) as zip_ref:\n            file_count = 0\n            for source_path in source_paths:\n                if os.path.isfile(source_path):\n                    zip_ref.write(source_path, os.path.basename(source_path))\n                    file_count += 1\n                elif os.path.isdir(source_path):\n                    for root, dirs, files in os.walk(source_path):\n                        for file in files:\n                            file_path = os.path.join(root, file)\n                            arcname = os.path.relpath(file_path, os.path.dirname(source_path))\n                            zip_ref.write(file_path, arcname)\n                            file_count += 1\n\n        return {\n            'success': True,\n            'message': f'Created ZIP with {file_count} files',\n            'zipPath': zip_path,\n            'fileCount': file_count\n        }\n    except Exception as e:\n        return {'success': False, 'error': str(e)}",
    "enabled": true
  },
  {
    "name": "read_email_file",
    "description": "Read and parse a saved email file (.eml format)",
    "type": "function",
    "parameters": {"emailPath": "string"},
    "code": "def execute(params):\n    \"\"\"Read and parse a saved email file.\"\"\"\n    import email\n    from email.header import decode_header\n\n    email_path = params.get('emailPath')\n    if not email_path:\n        return {'success': False, 'error': 'emailPath parameter is required'}\n\n    try:\n        with open(email_path, 'rb') as f:\n            msg = email.message_from_bytes(f.read())\n\n        # Decode subject\n        subject = msg.get('Subject', '')\n        if subject:\n            decoded_parts = decode_header(subject)\n            subject = ''\n            for content, encoding in decoded_parts:\n                if isinstance(content, bytes):\n                    subject += content.decode(encoding or 'utf-8', errors='replace')\n                else:\n                    subject += content\n\n        from_addr = msg.get('From', '')\n        to_addr = msg.get('To', '')\n        date = msg.get('Date', '')\n        cc = msg.get('Cc', '')\n\n        # Extract body\n        body = ''\n        html_body = ''\n        if msg.is_multipart():\n            for part in msg.walk():\n                content_type = part.get_content_type()\n                if content_type == 'text/plain' and not body:\n                    try:\n                        body = part.get_payload(decode=True).decode('utf-8', errors='replace')\n                    except:\n                        body = str(part.get_payload())\n                elif content_type == 'text/html' and not html_body:\n                    try:\n                        html_body = part.get_payload(decode=True).decode('utf-8', errors='replace')\n                    except:\n                        html_body = str(part.get_payload())\n        else:\n            try:\n                body = msg.get_payload(decode=True).decode('utf-8', errors='replace')\n            except:\n                body = str(msg.get_payload())\n\n        # Get attachments info\n        attachments = []\n        if msg.is_multipart():\n            for part in msg.walk():\n                if part.get_content_disposition() == 'attachment':\n                    filename = part.get_filename()\n                    if filename:\n                        # Decode filename if needed\n                        if filename:\n                            decoded_parts = decode_header(filename)\n                            filename = ''\n                            for content, encoding in decoded_parts:\n                                if isinstance(content, bytes):\n                                    filename += content.decode(encoding or 'utf-8', errors='replace')\n                                else:\n                                    filename += content\n\n                        payload = part.get_payload(decode=True)\n                        attachments.append({\n                            'filename': filename,\n                            'content_type': part.get_content_type(),\n                            'size': len(payload) if payload else 0\n                        })\n\n        return {\n            'success': True,\n            'subject': subject,\n            'from': from_addr,\n            'to': to_addr,\n            'cc': cc,\n            'date': date,\n            'body': body,\n            'html_body': html_body,\n            'attachments': attachments,\n            'emailPath': email_path\n        }\n    except FileNotFoundError:\n        return {'success': False, 'error': f'Email file not found: {email_path}'}\n    except Exception as e:\n        return {'success': False, 'error': str(e)}",
    "enabled": true
  },
  {
    "name": "get_file_metadata",
    "description": "Get file metadata (size, dates, permissions)",
    "type": "function",
    "parameters": {"filePath": "string"},
    "code": "def execute(params):\n    \"\"\"Get file metadata.\"\"\"\n    import os\n    import stat\n    import datetime\n\n    file_path = params.get('filePath')\n    if not file_path:\n        return {'success': False, 'error': 'filePath parameter is required'}\n\n    try:\n        stats = os.stat(file_path)\n\n        return {\n            'success': True,\n            'path': file_path,\n            'size': stats.st_size,\n            'created': datetime.datetime.fromtimestamp(stats.st_ctime).isoformat(),\n            'modified': datetime.datetime.fromtimestamp(stats.st_mtime).isoformat(),\n            'accessed': datetime.datetime.fromtimestamp(stats.st_atime).isoformat(),\n            'permissions': oct(stat.S_IMODE(stats.st_mode)),\n            'is_file': os.path.isfile(file_path),\n            'is_directory': os.path.isdir(file_path)\n        }\n    except FileNotFoundError:\n        return {'success': False, 'error': f'File not found: {file_path}'}\n    except Exception as e:\n        return {'success': False, 'error': str(e)}",
    "enabled": true
  },
  {
    "name": "search_files",
    "description": "Search for files by name pattern in a directory",
    "type": "function",
    "parameters": {"directory": "string", "pattern": "string", "recursive": "boolean"},
    "code": "def execute(params):\n    \"\"\"Search for files by name pattern.\"\"\"\n    import os\n    import fnmatch\n\n    directory = params.get('directory')\n    pattern = params.get('pattern')\n\n    if not directory or not pattern:\n        return {'success': False, 'error': 'directory and pattern parameters are required'}\n\n    recursive = params.get('recursive', True)\n\n    try:\n        matches = []\n\n        if recursive:\n            for root, dirs, files in os.walk(directory):\n                for filename in fnmatch.filter(files, pattern):\n                    matches.append(os.path.join(root, filename))\n        else:\n            files = os.listdir(directory)\n            for filename in fnmatch.filter(files, pattern):\n                full_path = os.path.join(directory, filename)\n                if os.path.isfile(full_path):\n                    matches.append(full_path)\n\n        return {\n            'success': True,\n            'count': len(matches),\n            'files': matches\n        }\n    except Exception as e:\n        return {'success': False, 'error': str(e)}",
    "enabled": true
  },
  {
    "name": "download_file",
    "description": "Download a file from a URL",
    "type": "tool",
    "parameters": {"url": "string", "savePath": "string"},
    "code": "def execute(params):\n    \"\"\"Download a file from a URL.\"\"\"\n    import urllib.request\n    import os\n\n    url = params.get('url')\n    save_path = params.get('savePath')\n\n    if not url:\n        return {'success': False, 'error': 'url parameter is required'}\n\n    if not save_path:\n        save_path = os.path.basename(url)\n\n    try:\n        urllib.request.urlretrieve(url, save_path)\n        file_size = os.path.getsize(save_path)\n\n        return {\n            'success': True,\n            'message': f'Downloaded {file_size} bytes',\n            'savePath': save_path,\n            'size': file_size\n        }\n    except Exception as e:\n        return {'success': False, 'error': str(e)}",
    "enabled": true
  },
  {
    "name": "screenshot",
    "description": "Take a screenshot and save to file",
    "type": "tool",
    "parameters": {"savePath": "string"},
    "code": "def execute(params):\n    \"\"\"Take a screenshot.\"\"\"\n    save_path = params.get('savePath', 'screenshot.png')\n\n    try:\n        import mss\n\n        with mss.mss() as sct:\n            monitor = sct.monitors[1]\n            screenshot = sct.grab(monitor)\n            mss.tools.to_png(screenshot.rgb, screenshot.size, output=save_path)\n\n        return {\n            'success': True,\n            'message': f'Screenshot saved to {save_path}',\n            'savePath': save_path\n        }\n    except ImportError:\n        return {'success': False, 'error': 'mss module not installed. Install with: pip install mss'}\n    except Exception as e:\n        return {'success': False, 'error': str(e)}",
    "enabled": true
  },
  {
    "name": "convert_image",
    "description": "Convert image format (PNG, JPG, BMP, GIF, etc.)",
    "type": "tool",
    "parameters": {"inputPath": "string", "outputPath": "string", "format": "string"},
    "code": "def execute(params):\n    \"\"\"Convert image format.\"\"\"\n    input_path = params.get('inputPath')\n    output_path = params.get('outputPath')\n\n    if not input_path or not output_path:\n        return {'success': False, 'error': 'inputPath and outputPath parameters are required'}\n\n    format_param = params.get('format', '').upper()\n\n    try:\n        from PIL import Image\n\n        img = Image.open(input_path)\n\n        if format_param:\n            img.save(output_path, format=format_param)\n        else:\n            img.save(output_path)\n\n        return {\n            'success': True,\n            'message': f'Image converted: {input_path} -> {output_path}',\n            'inputPath': input_path,\n            'outputPath': output_path,\n            'format': format_param if format_param else 'auto'\n        }\n    except ImportError:\n        return {'success': False, 'error': 'PIL (Pillow) not installed. Install with: pip install pillow'}\n    except Exception as e:\n        return {'success': False, 'error': str(e)}",
    "enabled": true
  },
  {
    "name": "list_processes",
    "description": "List running processes with PID, name, CPU%, and memory usage (cross-platform)",
    "type": "command",
    "parameters": {"sort_by": "string", "limit": "number"},
    "code": "def execute(params):\n    \"\"\"List running processes.\"\"\"\n    import platform\n    import subprocess\n\n    sort_by = params.get('sort_by', 'pid')\n    limit = params.get('limit', 50)\n    system = platform.system().lower()\n    processes = []\n\n    try:\n        if system == 'windows':\n            cmd = 'tasklist /fo csv /nh'\n            result = subprocess.run(cmd, shell=True, capture_output=True, text=True, timeout=30)\n            lines = result.stdout.strip().split('\\n')\n            for line in lines:\n                if line.strip():\n                    parts = line.strip().split('\",\"')\n                    if len(parts) >= 5:\n                        name = parts[0].strip('\"')\n                        pid = parts[1].strip('\"')\n                        mem = parts[4].strip('\"').replace(' K', '').replace(',', '')\n                        try:\n                            processes.append({'pid': int(pid), 'name': name, 'cpu_percent': 0.0, 'memory_mb': int(mem) / 1024 if mem.isdigit() else 0})\n                        except ValueError:\n                            pass\n        else:\n            cmd = 'ps aux --no-headers' if system == 'linux' else 'ps aux'\n            result = subprocess.run(cmd, shell=True, capture_output=True, text=True, timeout=30)\n            lines = result.stdout.strip().split('\\n')\n            start_idx = 1 if system == 'darwin' else 0\n            for line in lines[start_idx:]:\n                if line.strip():\n                    parts = line.split()\n                    if len(parts) >= 11:\n                        try:\n                            processes.append({'pid': int(parts[1]), 'name': parts[10], 'cpu_percent': float(parts[2]), 'memory_mb': int(parts[5]) / 1024})\n                        except (ValueError, IndexError):\n                            pass\n\n        sort_key = sort_by.lower()\n        if sort_key == 'cpu':\n            processes.sort(key=lambda x: x['cpu_percent'], reverse=True)\n        elif sort_key in ('memory', 'mem'):\n            processes.sort(key=lambda x: x['memory_mb'], reverse=True)\n        elif sort_key == 'name':\n            processes.sort(key=lambda x: x['name'].lower())\n        else:\n            processes.sort(key=lambda x: x['pid'])\n\n        if limit and limit > 0:\n            processes = processes[:int(limit)]\n\n        return {'success': True, 'platform': system, 'count': len(processes), 'processes': processes}\n    except Exception as e:\n        return {'success': False, 'error': str(e)}",
    "enabled": true
  },
  {
    "name": "kill_process",
    "description": "Kill a process by PID or name (cross-platform)",
    "type": "command",
    "parameters": {"pid": "number", "name": "string"},
    "code": "def execute(params):\n    \"\"\"Kill a process by PID or name.\"\"\"\n    import platform\n    import subprocess\n    import os\n    import signal\n\n    pid = params.get('pid')\n    name = params.get('name')\n\n    if not pid and not name:\n        return {'success': False, 'error': 'Either pid or name parameter is required'}\n\n    system = platform.system().lower()\n    killed = []\n\n    try:\n        if pid:\n            pid = int(pid)\n            if system == 'windows':\n                result = subprocess.run(f'taskkill /PID {pid} /F', shell=True, capture_output=True, text=True, timeout=10)\n                if result.returncode == 0:\n                    killed.append({'pid': pid})\n                else:\n                    return {'success': False, 'error': result.stderr.strip()}\n            else:\n                os.kill(pid, signal.SIGTERM)\n                killed.append({'pid': pid})\n\n        if name:\n            if system == 'windows':\n                result = subprocess.run(f'taskkill /IM \"{name}\" /F', shell=True, capture_output=True, text=True, timeout=10)\n                if result.returncode == 0:\n                    killed.append({'name': name})\n            else:\n                result = subprocess.run(f'pkill -f \"{name}\"', shell=True, capture_output=True, text=True, timeout=10)\n                if result.returncode == 0:\n                    killed.append({'name': name})\n\n        return {'success': True, 'killed': killed} if killed else {'success': False, 'error': 'No processes killed'}\n    except Exception as e:\n        return {'success': False, 'error': str(e)}",
    "enabled": false
  },
  {
    "name": "start_process",
    "description": "Start a process in the background (cross-platform)",
    "type": "command",
    "parameters": {"command": "string", "args": "array"},
    "code": "def execute(params):\n    \"\"\"Start a process in the background.\"\"\"\n    import platform\n    import subprocess\n\n    command = params.get('command')\n    args = params.get('args', [])\n\n    if not command:\n        return {'success': False, 'error': 'command parameter is required'}\n\n    system = platform.system().lower()\n    full_cmd = [command] + [str(a) for a in args] if args else [command]\n\n    try:\n        if system == 'windows':\n            process = subprocess.Popen(full_cmd, stdout=subprocess.DEVNULL, stderr=subprocess.DEVNULL, stdin=subprocess.DEVNULL, creationflags=0x00000008)\n        else:\n            process = subprocess.Popen(full_cmd, stdout=subprocess.DEVNULL, stderr=subprocess.DEVNULL, stdin=subprocess.DEVNULL, start_new_session=True)\n\n        return {'success': True, 'pid': process.pid, 'command': command, 'args': args}\n    except FileNotFoundError:\n        return {'success': False, 'error': f'Command not found: {command}'}\n    except Exception as e:\n        return {'success': False, 'error': str(e)}",
    "enabled": false
  },
  {
    "name": "create_directory",
    "description": "Create a new directory (creates parent directories if needed)",
    "type": "function",
    "parameters": {"dirPath": "string"},
    "code": "def execute(params):\n    \"\"\"Create a new directory.\"\"\"\n    import os\n\n    dir_path = params.get('dirPath')\n    if not dir_path:\n        return {'success': False, 'error': 'dirPath parameter is required'}\n\n    try:\n        os.makedirs(dir_path, exist_ok=True)\n        return {\n            'success': True,\n            'message': f'Directory created: {dir_path}',\n            'dirPath': dir_path\n        }\n    except Exception as e:\n        return {'success': False, 'error': str(e)}",
    "enabled": true
  },
  {
    "name": "playwright_fetch",
    "description": "Fetch webpage content using Playwright browser with stealth mode (bypasses bot detection, handles JS-rendered pages)",
    "type": "tool",
    "parameters": {"url": "string", "urls": "array", "timeout": "number", "waitForJS": "boolean", "includeLinks": "boolean", "maxLength": "number"},
    "code": "# This skill is executed via the /api/playwright/fetch endpoint\n# Parameters:\n#   url (string): Single URL to fetch\n#   urls (array): Multiple URLs to fetch in parallel\n#   timeout (number): Timeout in ms (default: 15000)\n#   waitForJS (boolean): Wait for JavaScript to render (default: true)\n#   includeLinks (boolean): Extract links from page (default: false)\n#   maxLength (number): Max content length (default: 8000)\n#\n# Features:\n# - Browser pooling for fast execution\n# - Stealth mode with fingerprint randomization\n# - Handles JavaScript-rendered content\n# - Automatic bot detection avoidance\n# - Falls back to axios if Playwright unavailable",
    "enabled": true
  },
  {
    "name": "playwright_interact",
    "description": "Interact with a webpage (click, type, scroll) before extracting content (for complex sites requiring user actions)",
    "type": "tool",
    "parameters": {"url": "string", "actions": "array", "timeout": "number", "maxLength": "number"},
    "code": "# This skill is executed via the /api/playwright/interact endpoint\n# Parameters:\n#   url (string): URL to navigate to\n#   actions (array): Actions to perform, each with:\n#     - type: 'click', 'type', 'wait', 'scroll', 'waitForNavigation'\n#     - selector: CSS selector for click/type/wait\n#     - text: Text to type (for 'type' action)\n#     - timeout: Max wait time (for 'wait' and 'waitForNavigation')\n#   timeout (number): Overall timeout in ms (default: 30000)\n#   maxLength (number): Max content length (default: 8000)\n#\n# Example actions:\n#   [{\"type\": \"click\", \"selector\": \"button.accept-cookies\"}]\n#   [{\"type\": \"type\", \"selector\": \"input#search\", \"text\": \"query\"}]\n#   [{\"type\": \"scroll\"}]\n#   [{\"type\": \"waitForNavigation\"}]",
    "enabled": true
  },
  {
    "name": "web_search",
    "description": "Search the web using DuckDuckGo with optional Playwright content fetching (returns actual page content, not just snippets)",
    "type": "tool",
    "parameters": {"query": "string", "limit": "number", "fetchContent": "boolean", "contentLimit": "number", "timeRange": "string"},
    "code": "# This skill is executed via the /api/search endpoint\n# Parameters:\n#   query (string): Search query\n#   limit (number): Max number of results (default: 5)\n#   fetchContent (boolean): Fetch actual page content (default: false)\n#   contentLimit (number): Number of URLs to fetch content from (default: 3)\n#   timeRange (string): d/w/m/y for day/week/month/year filter\n#\n# Features:\n# - Auto-enhances 'recent/latest/news' queries with current date\n# - Uses Playwright for content fetching when available\n# - Falls back to axios for basic content extraction\n# - Caches results for 1 hour\n# - Returns extracted content including title, summary, headings, and paragraphs",
    "enabled": true
  }
]
